README.md
setup.py
UrlFit.egg-info/PKG-INFO
UrlFit.egg-info/SOURCES.txt
UrlFit.egg-info/dependency_links.txt
UrlFit.egg-info/entry_points.txt
UrlFit.egg-info/requires.txt
UrlFit.egg-info/top_level.txt
urlfit/__init__.py
urlfit/urlfit.py