Metadata-Version: 1.0
Name: UrlFit
Version: 1.1
Summary: UrlFit - Shorten your url
Home-page: https://url.fit
Author: Ze-Yan Lin
Author-email: zylin@url.fit
License: UNKNOWN
Platform: UNKNOWN
